LICENSE
async_casbin_sqlmodel_adapter/__init__.py
async_casbin_sqlmodel_adapter/adapter.py
async_casbin_sqlmodel_adapter/adapter.pyi
async_casbin_sqlmodel_adapter/models.py
async_casbin_sqlmodel_adapter-0.1.5.dist-info/LICENSE
async_casbin_sqlmodel_adapter-0.1.5.dist-info/METADATA
async_casbin_sqlmodel_adapter-0.1.5.dist-info/WHEEL
async_casbin_sqlmodel_adapter-0.1.5.dist-info/RECORD
