Metadata-Version: 2.1
Name: async-casbin-sqlmodel-adapter
Version: 0.1.5
Summary: Async SQLModel Adapter for PyCasbin
Home-page: https://github.com/shepilov-vladislav/sqlmodel-casbin-adapter
License: Apache-2.0
Keywords: pycasbin,asynccasbin,sqlmodel
Author: Vladislav Shepilov
Author-email: shepilov.v@protonmail.com
Requires-Python: >=3.10,<4.0
Classifier: License :: OSI Approved :: Apache Software License
Classifier: Programming Language :: Python :: 3
Classifier: Programming Language :: Python :: 3.10
Classifier: Programming Language :: Python :: 3.11
Classifier: Programming Language :: Python :: 3.12
Requires-Dist: SQLAlchemy[asyncio,mypy] (>=2.0.25,<3.0.0)
Requires-Dist: casbin-async-sqlalchemy-adapter (>=1.4.0,<2.0.0)
Requires-Dist: sqlmodel (>=0.0.14,<0.0.15)
Project-URL: Repository, https://github.com/shepilov-vladislav/sqlmodel-casbin-adapter
